invoke_toolkit/__init__.py
invoke_toolkit/__main__.py
invoke_toolkit/collections.py
invoke_toolkit/executor.py
invoke_toolkit/testing.py
invoke_toolkit/config/__init__.py
invoke_toolkit/config/config.py
invoke_toolkit/config/status_helper.py
invoke_toolkit/context/__init__.py
invoke_toolkit/context/context.py
invoke_toolkit/context/types.py
invoke_toolkit/extensions/__init__.py
invoke_toolkit/extensions/tasks/__init__.py
invoke_toolkit/extensions/tasks/config.py
invoke_toolkit/extensions/tasks/create.py
invoke_toolkit/extensions/tasks/dist.py
invoke_toolkit/loader/entrypoint.py
invoke_toolkit/log/__init__.py
invoke_toolkit/log/logger.py
invoke_toolkit/output/__init__.py
invoke_toolkit/output/console.py
invoke_toolkit/output/utils.py
invoke_toolkit/program/__init__.py
invoke_toolkit/program/main.py
invoke_toolkit/program/program.py
invoke_toolkit/runners/__init__.py
invoke_toolkit/runners/rich.py
invoke_toolkit/scripts/__init__.py
invoke_toolkit/scripts/loader.py
invoke_toolkit/tasks/__init__.py
invoke_toolkit/tasks/tasks.py
invoke_toolkit/utils/__init__.py
invoke_toolkit/utils/inspection.py
invoke_toolkit/utils/singleton.py
invoke_toolkit/utils/text.py
invoke_toolkit/templates/package-template/.gitignore.jinja
invoke_toolkit/templates/package-template/README.md.jinja
invoke_toolkit/templates/package-template/copier.yml
invoke_toolkit/templates/package-template/pyproject.toml.jinja
invoke_toolkit/templates/package-template/src/{{package_slug}}/__init__.py.jinja
invoke_toolkit/templates/package-template/src/{{package_slug}}/tasks.py.jinja
invoke_toolkit-0.0.43.dist-info/METADATA
invoke_toolkit-0.0.43.dist-info/WHEEL
invoke_toolkit-0.0.43.dist-info/entry_points.txt
invoke_toolkit-0.0.43.dist-info/licenses/LICENSE.txt
invoke_toolkit-0.0.43.dist-info/RECORD
