Metadata-Version: 2.4
Name: invoke-toolkit
Version: 0.0.43
Summary: A set of extended APIs for PyInvoke for composable scripts, plugins and richer output
Project-URL: Documentation, https://github.com/D3f0/invoke-toolkit#readme
Project-URL: Issues, https://github.com/D3f0/invoke-toolkit/issues
Project-URL: Source, https://github.com/D3f0/invoke-toolkit
Author-email: Nahuel Defossé <D3f0@users.noreply.github.com>
License-Expression: MIT
License-File: LICENSE.txt
Classifier: Development Status :: 4 - Beta
Classifier: Environment :: Console
Classifier: Operating System :: MacOS :: MacOS X
Classifier: Operating System :: POSIX
Classifier: Operating System :: Unix
Classifier: Programming Language :: Python
Classifier: Programming Language :: Python :: 3
Classifier: Programming Language :: Python :: Implementation :: CPython
Classifier: Topic :: Software Development
Classifier: Topic :: Software Development :: Build Tools
Classifier: Topic :: Software Development :: Libraries
Classifier: Topic :: Software Development :: Libraries :: Python Modules
Classifier: Topic :: System :: Software Distribution
Classifier: Topic :: System :: Systems Administration
Requires-Python: >=3.10
Requires-Dist: appdirs
Requires-Dist: copier>=9.10.3
Requires-Dist: invoke>=2.2.1
Requires-Dist: pdbpp>=0.11.7
Requires-Dist: pyyaml>=6.0.3
Requires-Dist: rich>=13
Requires-Dist: tomlkit>=0.13.3
Requires-Dist: typing-extensions>=4.13.2
Provides-Extra: dev
Requires-Dist: hunter>=3.7.0; extra == 'dev'
Requires-Dist: pdbpp>=0.11.7; extra == 'dev'
